LabTools/__init__.py
LabTools/fit.py
LabTools/latex.py
LabTools/measure.py
LabTools/plot.py
LabTools/utils/__init__.py
LabTools/utils/generic.py
LabTools/utils/significant_digits.py
LabTools/utils/uncertainties.py
labtools_arna-1.0.0.dist-info/LICENSE
labtools_arna-1.0.0.dist-info/METADATA
labtools_arna-1.0.0.dist-info/WHEEL
labtools_arna-1.0.0.dist-info/top_level.txt
labtools_arna-1.0.0.dist-info/RECORD
