Metadata-Version: 2.1
Name: labtools-arna
Version: 1.0.0
Summary: Tools for physics laborayory courses
Home-page: https://github.com/arn4/LabTools
Author: Luca Arnaboldi
Author-email: luca@arnaboldi.lu
License: GPLv3
Platform: UNKNOWN
Requires-Python: >=3.6
Requires-Dist: numpy
Requires-Dist: uncertainties
Requires-Dist: matplotlib
Requires-Dist: scipy
Requires-Dist: pyaml
